osv/__init__.py
osv/analyze_tool/__init__.py
osv/analyze_tool/__main__.py
osv/bug.py
osv/bug_test.py
osv/build_protos.sh
osv/cache.py
osv/cloudbuild.yaml
osv/ecosystems/__init__.py
osv/ecosystems/_ecosystems.py
osv/ecosystems/_ecosystems_test.py
osv/ecosystems/alpine.py
osv/ecosystems/alpine_test.py
osv/ecosystems/bioconductor.py
osv/ecosystems/bioconductor_test.py
osv/ecosystems/cassettes/BioconductorEcosystemTest.test_next_version.yaml
osv/ecosystems/cassettes/CRANEcosystemTest.test_next_version.yaml
osv/ecosystems/cassettes/DebianEcosystemTest.test_cache.yaml
osv/ecosystems/cassettes/DebianEcosystemTest.test_debian.yaml
osv/ecosystems/cassettes/GHCEcosystemTest.test_next_version.yaml
osv/ecosystems/cassettes/HackageEcosystemTest.test_next_version.yaml
osv/ecosystems/cassettes/MavenEcosystemTest.test_enumerate.yaml
osv/ecosystems/cassettes/MavenEcosystemTest.test_next_version.yaml
osv/ecosystems/cassettes/NuGetEcosystemTest.test_next_version.yaml
osv/ecosystems/cassettes/PackagistEcosystemTest.test_packagist.yaml
osv/ecosystems/cassettes/PubEcosystemTest.test_next_version.yaml
osv/ecosystems/cassettes/PyPIEcosystemTest.test_next_version.yaml
osv/ecosystems/cassettes/RubyGemsEcosystemTest.test_next_version.yaml
osv/ecosystems/config.py
osv/ecosystems/cran.py
osv/ecosystems/cran_test.py
osv/ecosystems/debian.py
osv/ecosystems/debian_test.py
osv/ecosystems/ecosystems_base.py
osv/ecosystems/ecosystems_test.py
osv/ecosystems/haskell.py
osv/ecosystems/haskell_test.py
osv/ecosystems/maven.py
osv/ecosystems/maven_test.py
osv/ecosystems/nuget.py
osv/ecosystems/nuget_test.py
osv/ecosystems/packagist.py
osv/ecosystems/packagist_test.py
osv/ecosystems/pub.py
osv/ecosystems/pub_test.py
osv/ecosystems/pypi.py
osv/ecosystems/pypi_test.py
osv/ecosystems/redhat.py
osv/ecosystems/redhat_test.py
osv/ecosystems/rubygems.py
osv/ecosystems/rubygems_test.py
osv/ecosystems/semver_ecosystem_helper.py
osv/ecosystems/semver_ecosystem_helper_test.py
osv/ecosystems/testdata/.gitignore
osv-0.1.2.dist-info/METADATA
osv-0.1.2.dist-info/WHEEL
osv-0.1.2.dist-info/licenses/LICENSE
osv-0.1.2.dist-info/RECORD
