Metadata-Version: 2.4
Name: osv
Version: 0.1.2
Summary: Open Source Vulnerabilities library
License-Expression: Apache-2.0
License-File: LICENSE
Author: OSV Authors
Author-email: osv-discuss@googlegroups.com
Requires-Python: >=3.13,<4.0
Classifier: Programming Language :: Python :: 3
Classifier: Programming Language :: Python :: 3.13
Classifier: Programming Language :: Python :: 3.14
Requires-Dist: attrs (>=23.2)
Requires-Dist: google-cloud-logging (>=3.10)
Requires-Dist: google-cloud-ndb (>=2.3)
Requires-Dist: google-cloud-pubsub (>=2.31.1)
Requires-Dist: google-cloud-storage (>=2.17)
Requires-Dist: grpcio (>=1.0)
Requires-Dist: jsonschema (>=4.0)
Requires-Dist: packageurl-python (>=0.17.0)
Requires-Dist: packaging-legacy (>=23.0.post0)
Requires-Dist: pygit2 (>=1.14.0)
Requires-Dist: pyyaml (>=6.0)
Requires-Dist: requests (>=2.32)
Requires-Dist: semver (>=3.0)
